state_access/__init__.py
state_access/turn_state.py
state_access/twiz_state.py
state_access/twiz_state_manager.py
state_access/user_state.py
twiz_state_dal_TWIZ_TEAM-0.0.8.dist-info/METADATA
twiz_state_dal_TWIZ_TEAM-0.0.8.dist-info/WHEEL
twiz_state_dal_TWIZ_TEAM-0.0.8.dist-info/top_level.txt
twiz_state_dal_TWIZ_TEAM-0.0.8.dist-info/RECORD
