Metadata-Version: 2.1
Name: twiz-state-dal-TWIZ-TEAM
Version: 0.0.8
Summary: State manager for alexa taskbot in remote modules. Requires aws key configured in order to access dynamoDB tables.
Home-page: https://github.com/pypa/sampleproject
Author: TWIZ-TEAM
Author-email: alexa-twiz@googlegroups.com
Project-URL: Bug Tracker, https://github.com/pypa/sampleproject/issues
Classifier: Programming Language :: Python :: 3
Classifier: License :: OSI Approved :: MIT License
Classifier: Operating System :: OS Independent
Requires-Python: >=3.6
